google/maps/routing/__init__.py
google/maps/routing/gapic_version.py
google/maps/routing/py.typed
google/maps/routing_v2/__init__.py
google/maps/routing_v2/gapic_metadata.json
google/maps/routing_v2/gapic_version.py
google/maps/routing_v2/py.typed
google/maps/routing_v2/services/__init__.py
google/maps/routing_v2/services/routes/__init__.py
google/maps/routing_v2/services/routes/async_client.py
google/maps/routing_v2/services/routes/client.py
google/maps/routing_v2/services/routes/transports/__init__.py
google/maps/routing_v2/services/routes/transports/base.py
google/maps/routing_v2/services/routes/transports/grpc.py
google/maps/routing_v2/services/routes/transports/grpc_asyncio.py
google/maps/routing_v2/services/routes/transports/rest.py
google/maps/routing_v2/services/routes/transports/rest_base.py
google/maps/routing_v2/types/__init__.py
google/maps/routing_v2/types/fallback_info.py
google/maps/routing_v2/types/geocoding_results.py
google/maps/routing_v2/types/localized_time.py
google/maps/routing_v2/types/location.py
google/maps/routing_v2/types/maneuver.py
google/maps/routing_v2/types/navigation_instruction.py
google/maps/routing_v2/types/polyline.py
google/maps/routing_v2/types/polyline_details.py
google/maps/routing_v2/types/route.py
google/maps/routing_v2/types/route_label.py
google/maps/routing_v2/types/route_modifiers.py
google/maps/routing_v2/types/route_travel_mode.py
google/maps/routing_v2/types/routes_service.py
google/maps/routing_v2/types/routing_preference.py
google/maps/routing_v2/types/speed_reading_interval.py
google/maps/routing_v2/types/toll_info.py
google/maps/routing_v2/types/toll_passes.py
google/maps/routing_v2/types/traffic_model.py
google/maps/routing_v2/types/transit.py
google/maps/routing_v2/types/transit_preferences.py
google/maps/routing_v2/types/units.py
google/maps/routing_v2/types/vehicle_emission_type.py
google/maps/routing_v2/types/vehicle_info.py
google/maps/routing_v2/types/waypoint.py
google_maps_routing-0.8.0.dist-info/licenses/LICENSE
google_maps_routing-0.8.0.dist-info/METADATA
google_maps_routing-0.8.0.dist-info/WHEEL
google_maps_routing-0.8.0.dist-info/top_level.txt
google_maps_routing-0.8.0.dist-info/RECORD
